{
  "resourceType": "CodeSystem",
  "id": "code-system-condition-category-my-core",
  "text": {
    "status": "generated",
    "div": "<div xmlns=\"http://www.w3.org/1999/xhtml\"><h2>CodeSystemConditionCategory (MY Core)</h2><tt>http://fhir.hie.moh.gov.my/CodeSystem/condition-category-my-core</tt><p>Code System condition category in Malaysia</p></div>"
  },
  "url": "http://fhir.hie.moh.gov.my/CodeSystem/condition-category-my-core",
  "name": "CodeSystemConditionCategoryMyCore",
  "title": "CodeSystemConditionCategory (MY Core)",
  "status": "active",
  "date": "2024-02-12T04:04:09.5621857+00:00",
  "description": "Code System condition category in Malaysia",
  "compositional": false,
  "content": "complete",
  "count": 2,
  "concept": [
    {
      "code": "dental-alert",
      "display": "Dental Alert",
      "definition": "Dental Alert"
    },
    {
      "code": "death-certificate",
      "display": "Death Certificate",
      "definition": "Death Certificate"
    }
  ]
}